fastapi_misskey/__init__.py
fastapi_misskey/client.py
fastapi_misskey/config.py
fastapi_misskey/exceptions.py
fastapi_misskey/utils.py
fastapi_misskey/models/__init__.py
fastapi_misskey/models/user.py
fastapi_misskey-0.0.1.dist-info/LICENSE
fastapi_misskey-0.0.1.dist-info/METADATA
fastapi_misskey-0.0.1.dist-info/WHEEL
fastapi_misskey-0.0.1.dist-info/top_level.txt
fastapi_misskey-0.0.1.dist-info/RECORD
