Metadata-Version: 2.1
Name: fastapi-misskey
Version: 0.0.1
Summary: Misskey authentication to FastAPI
Home-page: https://github.com/yupix/fastapi-misskey
Author: yupix
License: MIT
Keywords: misskey,fastapi
Platform: UNKNOWN
Classifier: License :: OSI Approved :: MIT License
Classifier: Programming Language :: Python :: 3.5
Classifier: Programming Language :: Python :: 3.6
Classifier: Programming Language :: Python :: 3.7
Classifier: Programming Language :: Python :: 3.8
Classifier: Programming Language :: Python :: 3.9
Classifier: Programming Language :: Python :: 3.10
Classifier: Topic :: Software Development :: Libraries :: Python Modules
Requires-Python: >=3.5
Requires-Dist: aiocache (==0.11.1)
Requires-Dist: aiohttp (==3.8.1)
Requires-Dist: fastapi (==0.70.0)
Requires-Dist: uvicorn (==0.15.0)
